apollo_settings/__init__.py
apollo_settings/client.py
apollo_settings/core.py
apollo_settings/version.py
apollo_settings-0.2.0.dist-info/LICENSE
apollo_settings-0.2.0.dist-info/METADATA
apollo_settings-0.2.0.dist-info/WHEEL
apollo_settings-0.2.0.dist-info/RECORD
