Metadata-Version: 2.1
Name: apollo-settings
Version: 0.2.0
Summary: Apollo Config & Pydantic Settings
License: MIT
Author: wangyuxin
Author-email: wangyuxin@mokahr.com
Requires-Python: >=3.8,<4.0
Classifier: License :: OSI Approved :: MIT License
Classifier: Programming Language :: Python :: 3
Classifier: Programming Language :: Python :: 3.8
Classifier: Programming Language :: Python :: 3.9
Classifier: Programming Language :: Python :: 3.10
Classifier: Programming Language :: Python :: 3.11
Classifier: Programming Language :: Python :: 3.12
Requires-Dist: pydantic (>=2.0.0,<3.0.0)
Requires-Dist: pydantic-settings (>=2.0.0,<3.0.0)
Requires-Dist: requests (>=2.0.0,<3.0.0)
